{
  "$schema": "https://mintlify.com/schema.json",
  "name": "Liquidify",
  "theme": "mint",
  "logo": {
    "light": "/Logo.svg",
    "dark": "/Logo.svg"
  },
  "favicon": "/Favicon.svg",
  "colors": {
    "primary": "#0071e3",
    "light": "#aeaeb2",
    "dark": "#1c1c1e"
  },
  "tabs": [
    {
      "name": "Documentation",
      "url": "docs"
    }
  ],
  "navigation": [
    {
      "group": "Getting Started",
      "pages": ["index", "getting-started/installation", "getting-started/quickstart", "snippets"]
    }
  ],
  "footerSocials": {
    "github": "https://github.com/tuliopc23/LiqUIdify"
  }
}
